Metadata-Version: 1.0
Name: nrm-distributions
Version: 1.2
Summary: Gaussian and Binomial distributions
Home-page: UNKNOWN
Author: ['Nkanyiso Mantengu']
Author-email: ['mantengunr@gmail.com']
License: UNKNOWN
Platform: UNKNOWN
